secpack/__init__.py
secpack/archiving.py
secpack/encryption.py
secpack/fetching.py
secpack/git_url.py
secpack/hashing.py
secpack/logger.py
secpack/main.py
secpack/security.py
secpack-0.1.0.dist-info/LICENSE
secpack-0.1.0.dist-info/METADATA
secpack-0.1.0.dist-info/WHEEL
secpack-0.1.0.dist-info/entry_points.txt
secpack-0.1.0.dist-info/top_level.txt
secpack-0.1.0.dist-info/RECORD
