Metadata-Version: 2.1
Name: secpack
Version: 0.1.0
Summary: secpack is a secure and flexible command-line tool for encrypting, decrypting, packaging, executing, and installing Python projects or arbitrary folders from local paths, URLs, or GitHub repositories.
Home-page: https://github.com/zwalloc/secpack
Author: AleirJDawn
Author-email: 
Classifier: Programming Language :: Python :: 3
Classifier: License :: OSI Approved :: MIT License
Requires-Python: >=3.6
License-File: LICENSE
Requires-Dist: cryptography
Requires-Dist: requests
Requires-Dist: colorama
